lamdata_arias/__init__.py
lamdata_arias/df_utils.py
lamdata_arias-0.1.dist-info/METADATA
lamdata_arias-0.1.dist-info/WHEEL
lamdata_arias-0.1.dist-info/top_level.txt
lamdata_arias-0.1.dist-info/RECORD
